LICENSE.txt
MANIFEST.in
README.rst
setup.py
django_ripozo/__init__.py
django_ripozo/admin.py
django_ripozo/dispatcher.py
django_ripozo/easy_resources.py
django_ripozo/exceptions.py
django_ripozo/manager.py
django_ripozo/models.py
django_ripozo/tests.py
django_ripozo/views.py
django_ripozo.egg-info/PKG-INFO
django_ripozo.egg-info/SOURCES.txt
django_ripozo.egg-info/dependency_links.txt
django_ripozo.egg-info/requires.txt
django_ripozo.egg-info/top_level.txt
django_ripozo/migrations/__init__.py